aett/eventstore/__init__.py
aett/eventstore/base_event.py
aett/eventstore/commit.py
aett/eventstore/constants.py
aett/eventstore/domain_event.py
aett/eventstore/event_message.py
aett/eventstore/i_access_snapshots.py
aett/eventstore/i_access_snapshots_async.py
aett/eventstore/i_commit_events.py
aett/eventstore/i_commit_events_async.py
aett/eventstore/i_manage_persistence.py
aett/eventstore/i_manage_persistence_async.py
aett/eventstore/memento.py
aett/eventstore/snapshot.py
aett/eventstore/stream_head.py
aett/eventstore/topic.py
aett/eventstore/topic_map.py
aett_eventstore-2.1.0.dist-info/LICENSE
aett_eventstore-2.1.0.dist-info/METADATA
aett_eventstore-2.1.0.dist-info/WHEEL
aett_eventstore-2.1.0.dist-info/top_level.txt
aett_eventstore-2.1.0.dist-info/RECORD
