Metadata-Version: 2.1
Name: aett-eventstore
Version: 2.1.0
Summary: Event store for Python
Author-email: Jacob Reimers <pypi@reimers.io>
License: MIT License
Project-URL: Homepage, https://github.com/jjrdk/aett
Keywords: events,event store,event sourcing
Classifier: License :: OSI Approved :: MIT License
Classifier: Programming Language :: Python
Classifier: Programming Language :: Python :: 3
Requires-Python: >=3.10
License-File: LICENSE
Requires-Dist: pydantic>=2.9.1
Provides-Extra: dev
Requires-Dist: pip-tools; extra == "dev"
Requires-Dist: pytest; extra == "dev"
Requires-Dist: behave; extra == "dev"
